kracknet/__init__.py
kracknet/analyzer.py
kracknet/kracknet.py
kracknet/prediction.py
kracknet/anonymizer/__init__.py
kracknet/anonymizer/analyzer.py
kracknet/anonymizer/prediction.py
kracknet/road_analyzer/__init__.py
kracknet/road_analyzer/analyzer.py
kracknet/road_analyzer/prediction.py
kracknet/utils/__init__.py
kracknet/utils/batch_prediction.py
kracknet/utils/blur.py
kracknet/utils/config.py
kracknet/utils/dataclass.py
kracknet/utils/decorators.py
kracknet/utils/image_format.py
kracknet/utils/performance.py
kracknet/utils/plot.py
kracknet/utils/video_processor.py
kracknet-0.4.12.dist-info/LICENSE
kracknet-0.4.12.dist-info/METADATA
kracknet-0.4.12.dist-info/WHEEL
kracknet-0.4.12.dist-info/entry_points.txt
kracknet-0.4.12.dist-info/top_level.txt
kracknet-0.4.12.dist-info/RECORD
