Metadata-Version: 2.1
Name: kracknet
Version: 0.4.12
Summary: KrackNet Client
Home-page: https://kracknet.com
Download-URL: https://pypi.python.org/pypi/kracknet
Author: Hans Roh
Author-email: hansroh@gmail.com
License: MIT
Platform: posix
Platform: nt
Classifier: License :: OSI Approved :: MIT License
Classifier: Development Status :: 4 - Beta
Classifier: Topic :: Utilities
Classifier: Intended Audience :: Developers
Classifier: Programming Language :: Python
Classifier: Programming Language :: Python :: 3
License-File: LICENSE
Requires-Dist: numpy <2
Requires-Dist: opencv-python
Requires-Dist: matplotlib
Requires-Dist: requests
Requires-Dist: rs4
Requires-Dist: click
Requires-Dist: toml
Requires-Dist: boto3
Requires-Dist: pillow
Requires-Dist: pillow-avif-plugin
